llama_index/retrievers/vectorize/__init__.py
llama_index/retrievers/vectorize/base.py
llama_index_retrievers_vectorize-0.2.1.dist-info/METADATA
llama_index_retrievers_vectorize-0.2.1.dist-info/WHEEL
llama_index_retrievers_vectorize-0.2.1.dist-info/RECORD
